sciaiot/__init__.py
sciaiot/py.typed
sciaiot/airflow/__init__.py
sciaiot/airflow/providers/__init__.py
sciaiot/airflow/providers/tdengine/__init__.py
sciaiot/airflow/providers/tdengine/hooks/__init__.py
sciaiot/airflow/providers/tdengine/hooks/tdengine.py
sciaiot/airflow/providers/tdengine/operators/__init__.py
sciaiot/airflow/providers/tdengine/operators/tdengine.py
sciaiot_airflow_providers_tdengine-0.1.7.dist-info/licenses/LICENSE
sciaiot_airflow_providers_tdengine-0.1.7.dist-info/METADATA
sciaiot_airflow_providers_tdengine-0.1.7.dist-info/WHEEL
sciaiot_airflow_providers_tdengine-0.1.7.dist-info/entry_points.txt
sciaiot_airflow_providers_tdengine-0.1.7.dist-info/top_level.txt
sciaiot_airflow_providers_tdengine-0.1.7.dist-info/RECORD
